crispr_array_generator
