Metadata-Version: 2.1
Name: crispr-array-generator
Version: 0.4
Summary: A tool to automate the design of CRISPR Cas12 arrays
Home-page: https://github.com/wachern/crispr_array_generator
Author: Willow Chernoske
Author-email: wachern@uw.edu
Classifier: Development Status :: 3 - Alpha
Classifier: Intended Audience :: Science/Research
Classifier: Topic :: Scientific/Engineering
Classifier: License :: OSI Approved :: MIT License
Classifier: Programming Language :: Python :: 3.9
Classifier: Programming Language :: Python :: 3.10
Classifier: Programming Language :: Python :: 3.11
License-File: LICENSE
Requires-Dist: openpyxl
